bin/A1Q1a.v
// Structural model for a 3-input AND gate
module and3(input a, b, c, output y); 
  and g1(y, a, b, c); // AND gate instantiation
endmodule

// Testbench for the 3-input AND gate
module tb_and3;
  reg a, b, c;  // Declare input signals as reg  
  wire y;       // Declare output signal as wire

  // Instantiate the and3 module
  and3 uut (.a(a), .b(b), .c(c), .y(y));

  initial begin
    #1;  // Ensure the simulation starts properly

    // Initialize the VCD file for GTKWave
    $dumpfile("and3.vcd");
    $dumpvars(0, tb_and3);

    // Monitor the signal values
    $monitor("Time %t, a = %b, b = %b, c = %b, y = %b", $time, a, b, c, y);

    // Test cases
    #10; a = 1'b0; b = 1'b0; c = 1'b0;
    #10; a = 1'b0; b = 1'b0; c = 1'b1;
    #10; a = 1'b0; b = 1'b1; c = 1'b0;
    #10; a = 1'b0; b = 1'b1; c = 1'b1;
    #10; a = 1'b1; b = 1'b0; c = 1'b0;
    #10; a = 1'b1; b = 1'b0; c = 1'b1;
    #10; a = 1'b1; b = 1'b1; c = 1'b0;
    #10; a = 1'b1; b = 1'b1; c = 1'b1;

    $finish; // End simulation
  end
endmodule

bin/and3.vcd
$date
	Tue Nov 19 19:07:56 2024
$end
$version
	Icarus Verilog
$end
$timescale
	1s
$end
$scope module tb_and3 $end
$var wire 1 ! y $end
$var reg 1 " a $end
$var reg 1 # b $end
$var reg 1 $ c $end
$scope module uut $end
$var wire 1 % a $end
$var wire 1 & b $end
$var wire 1 ' c $end
$var wire 1 ! y $end
$upscope $end
$upscope $end
$enddefinitions $end
#1
$dumpvars
x'
x&
x%
x$
x#
x"
x!
$end
#11
0!
0$
0'
0#
0&
0"
0%
#21
1$
1'
#31
0$
0'
1#
1&
#41
1$
1'
#51
0$
0'
0#
0&
1"
1%
#61
1$
1'
#71
0$
0'
1#
1&
#81
1!
1$
1'
