bin/counter.v
/*  Problem 3: Design a verilog module of counter that counts from 7 to 0 (e.g.,
 7, 6, 5, 4, 3, 2, 1, 0). */

module counter(input clk, reset, en, output reg [2:0] count);

always @(posedge clk or negedge reset)
begin
    if (reset) 
        count <= 3'b111; // Reset count to 7
    else if (en) 
        if (count > 0) 
            count <= count - 1; // Decrement counter
        else
            count <= 3'b111; // Reset to 7 if counter reaches 0
end

endmodule 

module tb_counter;
    reg clk, reset, en;
    wire [2:0] count;

    // Instantiate the counter module
    counter uut (.clk(clk), .reset(reset), .en(en), .count(count));

    // Clock generation: toggle every 5 ns
    always #5 clk = ~clk;

    initial begin
        // Initialize signals
        clk = 0; 
        reset = 0; 
        en = 0;

        // Set up VCD for waveform dumping
        $dumpfile("counter.vcd");
        $dumpvars(0, tb_counter);

        // Apply reset
        #10 reset = 1;
        #10 reset = 0;

        // Enable counter and run it
        #10 en = 1;
        #100 en = 0; // Stop the counter after 100 ns

        // End simulation
        $finish;
    end

    // Monitor the count value
    initial begin
        $monitor("Time = %t, Count = %b", $time, count);
    end
endmodule

bin/counter.vcd
$date
	Sun Dec 01 13:47:03 2024
$end
$version
	Icarus Verilog
$end
$timescale
	1s
$end
$scope module tb_counter $end
$var wire 3 ! count [2:0] $end
$var reg 1 " clk $end
$var reg 1 # en $end
$var reg 1 $ reset $end
$scope module uut $end
$var wire 1 % clk $end
$var wire 1 & en $end
$var wire 1 ' reset $end
$var reg 3 ( count [2:0] $end
$upscope $end
$upscope $end
$enddefinitions $end
#0
$dumpvars
bx (
0'
0&
0%
0$
0#
0"
bx !
$end
#5
1"
1%
#10
0"
0%
1$
1'
#15
b111 (
b111 !
1"
1%
#20
0"
0%
0$
0'
#25
1"
1%
#30
0"
0%
1#
1&
#35
b110 (
b110 !
1"
1%
#40
0"
0%
#45
b101 (
b101 !
1"
1%
#50
0"
0%
#55
b100 (
b100 !
1"
1%
#60
0"
0%
#65
b11 (
b11 !
1"
1%
#70
0"
0%
#75
b10 (
b10 !
1"
1%
#80
0"
0%
#85
b1 (
b1 !
1"
1%
#90
0"
0%
#95
b0 (
b0 !
1"
1%
#100
0"
0%
#105
b111 (
b111 !
1"
1%
#110
0"
0%
#115
b110 (
b110 !
1"
1%
#120
0"
0%
#125
b101 (
b101 !
1"
1%
#130
0"
0%
0#
0&
