bin/d3.v
/* Divide the Clock Frequency by 3 */





module d3(input clk, reset, output q);

   reg [1:0] s, ns; // State (s) and next state (ns)

   parameter s0 = 2'b00;
   parameter s1 = 2'b01; 
   parameter s2 = 2'b10;

   // State register with asynchronous reset
   always @ (posedge clk or negedge reset)
      if (!reset) 
         s <= s0; // Set state to s0 on reset
      else 
         s <= ns; // Update state to next state

   // Next-state logic
   always @(*)
      case (s)
         s0: ns = s1;
         s1: ns = s2;
         s2: ns = s0;
         default: ns = s0;
      endcase

   // Output logic
   assign q = (s == s0); // Output is high only in state s0

endmodule

module tb_d3;
   reg clk, reset; // Clock and reset signals
   wire q;         // Output wire

   // Instantiate the DUT (Design Under Test)
   d3 uut(.clk(clk), .reset(reset), .q(q));

   // Generate clock signal
   initial begin
      clk = 0;
      forever #5 clk = ~clk; // Toggle clock every 5 time units
   end

   // Apply test stimulus
   initial begin
      $dumpfile("d3.vcd");      // Specify VCD file for waveform
      $dumpvars(0, tb_d3);      // Dump all variables in testbench
      $monitor("Time = %t, clk = %b, reset = %b, q = %b", $time, clk, reset, q);

      // Initialize and apply test inputs
      reset = 0;               // Assert reset
      #10 reset = 1;           // Release reset
      #50 reset = 0;           // Assert reset again
      #10 reset = 1;           // Release reset
      #50;                     // Wait for a few clock cycles

      $finish;                 // End simulation
   end
endmodule

bin/d3.vcd
$date
	Sat Nov 30 21:15:16 2024
$end
$version
	Icarus Verilog
$end
$timescale
	1s
$end
$scope module tb_d3 $end
$var wire 1 ! q $end
$var reg 1 " clk $end
$var reg 1 # reset $end
$scope module uut $end
$var wire 1 $ clk $end
$var wire 1 ! q $end
$var wire 1 % reset $end
$var reg 2 & ns [1:0] $end
$var reg 2 ' s [1:0] $end
$upscope $end
$upscope $end
$enddefinitions $end
#0
$dumpvars
b0 '
b1 &
0%
0$
0#
0"
1!
$end
#5
1"
1$
#10
0"
0$
1#
1%
#15
b10 &
b1 '
0!
1"
1$
#20
0"
0$
#25
b0 &
b10 '
1"
1$
#30
0"
0$
#35
b1 &
b0 '
1!
1"
1$
#40
0"
0$
#45
b10 &
b1 '
0!
1"
1$
#50
0"
0$
#55
b0 &
b10 '
1"
1$
#60
b1 &
b0 '
1!
0"
0$
0#
0%
#65
1"
1$
#70
0"
0$
1#
1%
#75
b10 &
b1 '
0!
1"
1$
#80
0"
0$
#85
b0 &
b10 '
1"
1$
#90
0"
0$
#95
b1 &
b0 '
1!
1"
1$
#100
0"
0$
#105
b10 &
b1 '
0!
1"
1$
#110
0"
0$
#115
b0 &
b10 '
1"
1$
