bin/FA.v
// A1 Q3
// Full Adder Module (Structural)
module FA(input A, B, C, output COUT, S);

    wire x, y, z;  // Intermediate wires

    // XOR gate for Sum
    xor g1(S, A, B, C);

    // AND gates for carry generation
    and g2(y, A, B);
    and g3(z, C, x);

    // OR gate for final carry out (COUT)
    or g4(x, A, B);
    or g5(COUT, y, z);

endmodule

// Testbench for Full Adder (FA)
module tb_FA;
    reg A, B, C;   // Inputs to the FA
    wire COUT, S;  // Outputs from the FA

    // Instantiate the Full Adder (FA)
    FA uut(.A(A), .B(B), .C(C), .COUT(COUT), .S(S));

    // Stimulate the inputs and observe the outputs
    initial begin
        // Generate the VCD file for waveform dumping
        $dumpfile("FA.vcd");  // Corrected the file name
        $dumpvars(0, tb_FA);  // Dump all signals in tb_FA module

        // Monitor the values of inputs and outputs
        $monitor("Time %t, A = %b, B = %b, C = %b, COUT = %b, S = %b", $time, A, B, C, COUT, S);

        // Apply stimulus (input values for different time steps)
        #10 A = 0; B = 0; C = 0;
        #10 A = 0; B = 0; C = 1;
        #10 A = 0; B = 1; C = 0;
        #10 A = 0; B = 1; C = 1;
        #10 A = 1; B = 0; C = 0;
        #10 A = 1; B = 0; C = 1;
        #10 A = 1; B = 1; C = 0;
        #10 A = 1; B = 1; C = 1;

        $finish;  // End the simulation
    end 
endmodule

bin/FA.vcd
$date
	Thu Nov 21 14:54:58 2024
$end
$version
	Icarus Verilog
$end
$timescale
	1s
$end
$scope module tb_FA $end
$var wire 1 ! COUT $end
$var wire 1 " S $end
$var reg 1 # A $end
$var reg 1 $ B $end
$var reg 1 % C $end
$scope module uut $end
$var wire 1 & A $end
$var wire 1 ' B $end
$var wire 1 ( C $end
$var wire 1 ! COUT $end
$var wire 1 " S $end
$var wire 1 ) x $end
$var wire 1 * y $end
$var wire 1 + z $end
$upscope $end
$upscope $end
$enddefinitions $end
#0
$dumpvars
x+
x*
x)
x(
x'
x&
x%
x$
x#
x"
x!
$end
#10
0!
0+
0"
0*
0)
0%
0(
0$
0'
0#
0&
#20
1"
1%
1(
#30
1)
0%
0(
1$
1'
#40
1!
0"
1+
1%
1(
#50
0!
0+
1"
0%
0(
0$
0'
1#
1&
#60
1!
0"
1+
1%
1(
#70
0+
1*
0%
0(
1$
1'
#80
1"
1+
1%
1(
