bin/gates.v
// 3-input AND Gate using structural modeling
module and_gate (
    input a,
    input b,
    input c,
    output y
);
    wire ab_and; // Intermediate wire for AND operation

    // Instantiate two 2-input AND gates
    and u1 (ab_and, a, b); // AND gate for a and b
    and u2 (y, ab_and, c); // AND gate for ab_and and c
endmodule

// 3-input OR Gate using structural modeling
module or_gate (
    input a,
    input b,
    input c,
    output y
);
    wire ab_or; // Intermediate wire for OR operation

    // Instantiate two 2-input OR gates
    or u1 (ab_or, a, b); // OR gate for a and b
    or u2 (y, ab_or, c); // OR gate for ab_or and c
endmodule

// Testbench to verify the gates
module testbench;
    reg a, b, c;
    wire and_out, or_out;

    // Instantiate the AND gate
    and_gate u1 (
        .a(a),
        .b(b),
        .c(c),
        .y(and_out)
    );

    // Instantiate the OR gate
    or_gate u2 (
        .a(a),
        .b(b),
        .c(c),
        .y(or_out)
    );

    initial begin
$dumpfile("gates.vcd"); // Create VCD file
    $dumpvars(0, testbench); // Dump all variables in the testbench
        // Monitor outputs
        $monitor("Time: %0t | a: %b, b: %b, c: %b | AND Output: %b | OR Output: %b", $time, a, b, c, and_out, or_out);
        
        // Test cases
        a = 0; b = 0; c = 0; #10;
        a = 0; b = 0; c = 1; #10;
        a = 0; b = 1; c = 0; #10;
        a = 0; b = 1; c = 1; #10;
        a = 1; b = 0; c = 0; #10;
        a = 1; b = 0; c = 1; #10;
        a = 1; b = 1; c = 0; #10;
        a = 1; b = 1; c = 1; #10;

        // End simulation
        $finish;
    end
endmodule

bin/gates.vcd
$date
	Sat Sep 28 00:23:20 2024
$end
$version
	Icarus Verilog
$end
$timescale
	1s
$end
$scope module testbench $end
$var wire 1 ! and_out $end
$var wire 1 " or_out $end
$var reg 1 # a $end
$var reg 1 $ b $end
$var reg 1 % c $end
$scope module u1 $end
$var wire 1 & a $end
$var wire 1 ' ab_and $end
$var wire 1 ( b $end
$var wire 1 ) c $end
$var wire 1 ! y $end
$upscope $end
$scope module u2 $end
$var wire 1 & a $end
$var wire 1 * ab_or $end
$var wire 1 ( b $end
$var wire 1 ) c $end
$var wire 1 " y $end
$upscope $end
$upscope $end
$enddefinitions $end
#0
$dumpvars
0*
0)
0(
0'
0&
0%
0$
0#
0"
0!
$end
#10
1"
1%
1)
#20
1*
0%
0)
1$
1(
#30
1%
1)
#40
0%
0)
0$
0(
1#
1&
#50
1%
1)
#60
1'
0%
0)
1$
1(
#70
1!
1%
1)
