bin/tb_gate.v
module tb_gate;

  reg A, B, C;
  wire Y_and, Y_or;

  // Instantiate the 3-input AND gate
  and u1 (.Y(Y_and), .A(A), .B(B), .C(C));
  
  // Instantiate the 3-input OR gate
  or u2 (.Y(Y_or), .A(A), .B(B), .C(C));

  initial begin
    // Test different combinations of A, B, and C
    $monitor("Time: %0d | A=%b B=%b C=%b | AND Output=%b OR Output=%b", $time, A, B, C, Y_and, Y_or);
    
    // Test 0 0 0
    A = 0; B = 0; C = 0;
    #10;
    
    // Test 0 0 1
    A = 0; B = 0; C = 1;
    #10;

    // Test 0 1 0
    A = 0; B = 1; C = 0;
    #10;

    // Test 0 1 1
    A = 0; B = 1; C = 1;
    #10;

    // Test 1 0 0
    A = 1; B = 0; C = 0;
    #10;

    // Test 1 0 1
    A = 1; B = 0; C = 1;
    #10;

    // Test 1 1 0
    A = 1; B = 1; C = 0;
    #10;

    // Test 1 1 1
    A = 1; B = 1; C = 1;
    #10;
    
    // End simulation
    $finish;
  end

endmodule

bin/gate_test.vcd
$date
	Fri Sep 27 10:36:16 2024
$end
$version
	Icarus Verilog
$end
$timescale
	1s
$end
$scope module tb_gate $end
$var wire 1 ! Y_and $end
$var wire 1 " Y_or $end
$var reg 1 # A $end
$var reg 1 $ B $end
$var reg 1 % C $end
$scope module u1 $end
$var wire 1 & A $end
$var wire 1 ' B $end
$var wire 1 ( C $end
$var wire 1 ! Y $end
$upscope $end
$scope module u2 $end
$var wire 1 & A $end
$var wire 1 ' B $end
$var wire 1 ( C $end
$var wire 1 " Y $end
$upscope $end
$upscope $end
$enddefinitions $end
#0
$dumpvars
0(
0'
0&
0%
0$
0#
0"
0!
$end
#10
1"
1%
1(
#20
0%
0(
1$
1'
#30
1%
1(
#40
0%
0(
0$
0'
1#
1&
#50
1%
1(
#60
0%
0(
1$
1'
#70
1!
1%
1(
