bin/mux_4to1.v
module mux_4to1 (
    output Y,        // Output of the multiplexer
    input [1:0] S,   // 2-bit select input
    input I0, I1, I2, I3  // 4 data inputs
);

    wire S0_bar, S1_bar;  // Complementary select lines
    wire Y0, Y1, Y2, Y3;  // Intermediate outputs for each input line

    // Generate NOT S0 and NOT S1
    not (S0_bar, S[0]);
    not (S1_bar, S[1]);

    // AND gates for each input
    and (Y0, S1_bar, S0_bar, I0);  // Select I0 if S1=0, S0=0
    and (Y1, S1_bar, S[0], I1);    // Select I1 if S1=0, S0=1
    and (Y2, S[1], S0_bar, I2);    // Select I2 if S1=1, S0=0
    and (Y3, S[1], S[0], I3);      // Select I3 if S1=1, S0=1

    // OR gate to combine all paths
    or (Y, Y0, Y1, Y2, Y3);

endmodule


module tb_mux_4to1;

    reg [1:0] S;    // 2-bit select input
    reg I0, I1, I2, I3; // Data inputs
    wire Y;         // Output of the multiplexer

    // Instantiate the 4-to-1 MUX
    mux_4to1 mux(.Y(Y), .S(S), .I0(I0), .I1(I1), .I2(I2), .I3(I3));

    initial begin

$dumpfile("mux_4to1.vcd");
$dumpvars(0, tb_mux_4to1);


        // Monitor values
        $monitor("Time = %0d | S1 = %b, S0 = %b | I0 = %b, I1 = %b, I2 = %b, I3 = %b | Y = %b", 
                 $time, S[1], S[0], I0, I1, I2, I3, Y);

        // Test case 1: I0 = 1, all other inputs are 0
        I0 = 1; I1 = 0; I2 = 0; I3 = 0; S = 2'b00; #10;
        // Test case 2: I1 = 1, all other inputs are 0
        I0 = 0; I1 = 1; I2 = 0; I3 = 0; S = 2'b01; #10;
        // Test case 3: I2 = 1, all other inputs are 0
        I0 = 0; I1 = 0; I2 = 1; I3 = 0; S = 2'b10; #10;
        // Test case 4: I3 = 1, all other inputs are 0
        I0 = 0; I1 = 0; I2 = 0; I3 = 1; S = 2'b11; #10;

        // Test case 5: All inputs are different
        I0 = 1; I1 = 0; I2 = 1; I3 = 0;
        S = 2'b00; #10;  // Should select I0
        S = 2'b01; #10;  // Should select I1
        S = 2'b10; #10;  // Should select I2
        S = 2'b11; #10;  // Should select I3

        $finish;
    end

endmodule

bin/mux_4to1.vcd
$date
	Fri Sep 27 12:10:05 2024
$end
$version
	Icarus Verilog
$end
$timescale
	1s
$end
$scope module tb_mux_4to1 $end
$var wire 1 ! Y $end
$var reg 1 " I0 $end
$var reg 1 # I1 $end
$var reg 1 $ I2 $end
$var reg 1 % I3 $end
$var reg 2 & S [1:0] $end
$scope module mux $end
$var wire 1 ' I0 $end
$var wire 1 ( I1 $end
$var wire 1 ) I2 $end
$var wire 1 * I3 $end
$var wire 2 + S [1:0] $end
$var wire 1 , S0_bar $end
$var wire 1 - S1_bar $end
$var wire 1 ! Y $end
$var wire 1 . Y0 $end
$var wire 1 / Y1 $end
$var wire 1 0 Y2 $end
$var wire 1 1 Y3 $end
$upscope $end
$upscope $end
$enddefinitions $end
#0
$dumpvars
01
00
0/
1.
1-
1,
b0 +
0*
0)
0(
1'
b0 &
0%
0$
0#
1"
1!
$end
#10
0,
1/
1!
0.
b1 &
b1 +
1#
1(
0"
0'
#20
10
1,
0-
1!
0/
b10 &
b10 +
1$
1)
0#
0(
#30
0,
11
1!
00
b11 &
b11 +
1%
1*
0$
0)
#40
1.
1,
1-
1!
01
b0 &
b0 +
0%
0*
1$
1)
1"
1'
#50
0!
0.
0,
b1 &
b1 +
#60
1!
10
1,
0-
b10 &
b10 +
#70
0!
00
0,
b11 &
b11 +
