bin/q4.v
module q4(input a, b, c, d, output p, div);

assign p = ~a & ~b & c & ~d | ~a & ~b & c & d | ~a & b & ~c & d | ~a & b & c & d | a & ~b & c & d | a & b & ~c & d;

assign div = ~a & ~b & ~c & ~d | ~a & ~b & c & d | ~a & b & c & ~d | a & ~b & ~c & d | a & b & ~c & ~d | a & b & c & d ; 

endmodule

module tb_q4;
reg a, b, c, d;
wire p, div ;

q4 uut (.a(a), .b(b), .c(c), .d(d), .p(p), .div(div));

initial begin

$dumpfile("q4.vcd");
$dumpvars(0, tb_q4);
$monitor("Time %t, a = %b, b = %b, c = %b, d = %b, p = %b, div = %b", $time, a, b, c, d, p , div);
#10; a = 0; b = 0; c = 0; d = 0;
#10; a = 0; b = 0; c = 0; d = 1;
#10; a = 0; b = 0; c = 1; d = 0;
#10; a = 0; b = 0; c = 1; d = 1;
#10; a = 0; b = 1; c = 1; d = 0;
#10; a = 0; b = 1; c = 1; d = 1;
#10; a = 0; b = 1; c = 0; d = 0;

$finish;

end

endmodule

bin/q4.vcd
$date
	Sat Nov 30 22:20:11 2024
$end
$version
	Icarus Verilog
$end
$timescale
	1s
$end
$scope module tb_q4 $end
$var wire 1 ! div $end
$var wire 1 " p $end
$var reg 1 # a $end
$var reg 1 $ b $end
$var reg 1 % c $end
$var reg 1 & d $end
$scope module uut $end
$var wire 1 ' a $end
$var wire 1 ( b $end
$var wire 1 ) c $end
$var wire 1 * d $end
$var wire 1 ! div $end
$var wire 1 " p $end
$upscope $end
$upscope $end
$enddefinitions $end
#0
$dumpvars
x*
x)
x(
x'
x&
x%
x$
x#
x"
x!
$end
#10
1!
0"
0&
0*
0%
0)
0$
0(
0#
0'
#20
0!
1&
1*
#30
1"
0&
0*
1%
1)
#40
1!
1&
1*
#50
0"
0&
0*
1$
1(
#60
0!
1"
1&
1*
#70
0"
0&
0*
0%
0)
