bin/SmilingSnail.v
/* The Smiling Snail */

module SmilingSnail (
    input clk, 
    input reset,
    input number,
    output smile
);
    reg [1:0] state, nextstate;

    parameter S0 = 2'b00;
    parameter S1 = 2'b01;
    parameter S2 = 2'b10;
    parameter S3 = 2'b11;

    // State register
    always @(posedge clk or posedge reset)
        if (reset)
            state <= S0;
        else
            state <= nextstate;

    // Next state logic
    always @(*) begin
        case (state)
            S0: if (number) nextstate = S1; else nextstate = S0;
            S1: if (number) nextstate = S2; else nextstate = S0;
            S2: if (number) nextstate = S2; else nextstate = S3;
            S3: if (number) nextstate = S1; else nextstate = S0;
            default: nextstate = S0;
        endcase
    end

    // Output logic
    assign smile = (number & (state == S3));

endmodule

module tb_SmilingSnail;
    reg clk, reset, number;
    wire smile;

    // Instantiate the SmilingSnail module
    SmilingSnail uut (
        .clk(clk),
        .reset(reset),
        .number(number),
        .smile(smile)
    );

    // Clock generation
    initial begin
        clk = 0;
        forever #5 clk = ~clk;  // 10 time units clock period
    end

    // Test sequence
    initial begin
        $dumpfile("SmilingSnail.vcd");
        $dumpvars(0, tb_SmilingSnail);
        $monitor("Time = %0t | clk = %b | reset = %b | number = %b | state = %b | smile = %b", 
                 $time, clk, reset, number, uut.state, smile);

        reset = 1; number = 0;  // Initialize
        #10 reset = 0;          // Deassert reset
        #10 number = 1;         // S0 → S1
        #20 number = 1;         // S1 → S2
        #20 number = 0;         // S2 → S3
        #20 number = 1;         // S3 → S1
        #10 reset = 1;          // Assert reset
        #10 reset = 0; number = 1;  // Test reset behavior
        #50 $finish;            // End simulation
    end
endmodule

bin/SmilingSnail.vcd
$date
	Sat Nov 30 21:36:40 2024
$end
$version
	Icarus Verilog
$end
$timescale
	1s
$end
$scope module tb_SmilingSnail $end
$var wire 1 ! smile $end
$var reg 1 " clk $end
$var reg 1 # number $end
$var reg 1 $ reset $end
$scope module uut $end
$var wire 1 % clk $end
$var wire 1 & number $end
$var wire 1 ' reset $end
$var wire 1 ! smile $end
$var reg 2 ( nextstate [1:0] $end
$var reg 2 ) state [1:0] $end
$upscope $end
$upscope $end
$enddefinitions $end
#0
$dumpvars
b0 )
b0 (
1'
0&
0%
1$
0#
0"
0!
$end
#5
1"
1%
#10
0"
0%
0$
0'
#15
1"
1%
#20
b1 (
0"
0%
1#
1&
#25
b10 (
b1 )
1"
1%
#30
0"
0%
#35
b10 )
1"
1%
#40
0"
0%
#45
1"
1%
#50
0"
0%
#55
1"
1%
#60
b11 (
0"
0%
0#
0&
#65
b0 (
b11 )
1"
1%
#70
0"
0%
#75
b0 )
1"
1%
#80
b1 (
0"
0%
1#
1&
#85
b10 (
b1 )
1"
1%
#90
b1 (
b0 )
0"
0%
1$
1'
#95
1"
1%
#100
0"
0%
0$
0'
#105
b10 (
b1 )
1"
1%
#110
0"
0%
#115
b10 )
1"
1%
