bin/srl.v
/* Problem 1: Implement a verilog module of an SR latch with asynchronous
 enable and reset. */

module srl(input s, r, en, reset, output reg q, qn);

always @(*) begin
    if (reset) begin
        q = 0;       // Asynchronous reset
        qn = 1;
    end else if (en) begin
        if (s && ~r) begin
            q = 1;   // Set state
            qn = 0;
        end else if (~s && r) begin
            q = 0;   // Reset state
            qn = 1;
        end else if (~s && ~r) begin
            // Hold state
            q = q;
            qn = qn;
        end else begin
            q = 1'bx; // Invalid state
            qn = 1'bx;
        end
    end
end

endmodule

`timescale 1ns / 1ps


module tb_srl;
    reg s, r, en, reset;   // Testbench inputs
    wire q, qn;            // Testbench outputs

    // Instantiate the SR latch module
    srl uut(
        .s(s),
        .r(r),
        .en(en),     // Connect 'en' to the module
        .reset(reset),
        .q(q),
        .qn(qn)
    );

    initial begin
        $dumpfile("srl.vcd");
        $dumpvars(0, tb_srl);

        $monitor("Time = %t | reset = %b | en = %b | s = %b | r = %b | q = %b | qn = %b", 
                  $time, reset, en, s, r, q, qn);

        // Initialize inputs
        reset = 0; en = 0; s = 0; r = 0;

        // Apply asynchronous reset
        #5 reset = 1;
        #5 reset = 0;

        // Enable latch and apply inputs
        #5 en = 1; s = 1; r = 0;  // Set state
        #5 s = 0; r = 1;          // Reset state
        #5 s = 0; r = 0;          // Hold state
        #5 s = 1; r = 1;          // Invalid state

        // Disable latch
        #5 en = 0; s = 1; r = 0;

        // Test asynchronous reset again
        #5 reset = 1;
        #5 reset = 0;

        $finish;
    end

endmodule

bin/srl.vcd
$date
	Fri Nov 29 22:06:50 2024
$end
$version
	Icarus Verilog
$end
$timescale
	1ps
$end
$scope module tb_srl $end
$var wire 1 ! q $end
$var wire 1 " qn $end
$var reg 1 # en $end
$var reg 1 $ r $end
$var reg 1 % reset $end
$var reg 1 & s $end
$scope module uut $end
$var wire 1 ' en $end
$var wire 1 ( r $end
$var wire 1 ) reset $end
$var wire 1 * s $end
$var reg 1 + q $end
$var reg 1 , qn $end
$upscope $end
$upscope $end
$enddefinitions $end
#0
$dumpvars
x,
x+
0*
0)
0(
0'
0&
0%
0$
0#
x"
x!
$end
#5000
1,
1"
0+
0!
1%
1)
#10000
0%
0)
#15000
0,
0"
1+
1!
1&
1*
1#
1'
#20000
1,
1"
0+
0!
1$
1(
0&
0*
#25000
0$
0(
#30000
x,
x"
x+
x!
1$
1(
1&
1*
#35000
0$
0(
0#
0'
#40000
1,
1"
0+
0!
1%
1)
#45000
0%
0)
